lumaserv_domain_api/__init__.py
lumaserv_domain_api/contact.py
lumaserv_domain_api/domain.py
lumaserv_domain_api/nameserver.py
lumaserv_domain_api/zones.py
lumaserv_domain_api-0.0.7.dist-info/LICENSE
lumaserv_domain_api-0.0.7.dist-info/METADATA
lumaserv_domain_api-0.0.7.dist-info/WHEEL
lumaserv_domain_api-0.0.7.dist-info/top_level.txt
lumaserv_domain_api-0.0.7.dist-info/RECORD
