Metadata-Version: 2.1
Name: lumaserv-domain-api
Version: 0.0.7
Summary: API Wrapper for LumaServ Domain API
Home-page: https://github.com/EverHype-Systems/lumaserv-domain-api
Author: Adrijan Bajrami
Author-email: abajrami@everhype-systems.eu
License: UNKNOWN
Platform: UNKNOWN
Classifier: Programming Language :: Python :: 3
Classifier: License :: OSI Approved :: GNU General Public License v3 or later (GPLv3+)
Classifier: Operating System :: OS Independent
Requires-Python: >=3.6
